articon/__init__.py
articon/config.py
articon/features.py
articon/filters.py
articon/image.py
articon/models.py
articon/samplers.py
articon/sys.py
articon/utils.py
articon-0.0.1.dist-info/LICENSE
articon-0.0.1.dist-info/METADATA
articon-0.0.1.dist-info/WHEEL
articon-0.0.1.dist-info/top_level.txt
articon-0.0.1.dist-info/RECORD
