Metadata-Version: 2.1
Name: articon
Version: 0.0.1
Summary: Corpus-based, icon mosaicking art in Python
Home-page: https://github.com/felipetovarhenao/articon
Author: Felipe Tovar-Henao
Author-email: <felipe.tovar.henao@gmail.com>
License: OSI Approved :: ISC License (ISCL)
Keywords: mosaicking,emoji art,machine learning,yung jake
Classifier: Development Status :: 5 - Production/Stable
Classifier: Intended Audience :: Other Audience
Classifier: Natural Language :: English
Classifier: Operating System :: MacOS :: MacOS X
Classifier: Operating System :: Microsoft :: Windows
Classifier: Programming Language :: Python
License-File: LICENSE
Requires-Dist: numpy
Requires-Dist: typing-extensions
Requires-Dist: Pillow
Requires-Dist: opencv-python
Requires-Dist: scikit-learn
Requires-Dist: progress
